Metadata-Version: 2.4
Name: iflow_mcp_nagarjun226_food_tracker
Version: 0.1.0
Summary: Add your description here
Requires-Python: >=3.11
Requires-Dist: httpx>=0.28.1
Requires-Dist: mcp[cli]>=1.6.0
Requires-Dist: pydantic>=2.11.1
